.bumpversion.cfg
MANIFEST.in
README.md
TODO.txt
pypackage.mk
requirements.txt
setup.py
src/reprep/__init__.py
src/reprep/config.py
src/reprep/constants.py
src/reprep/datanode.py
src/reprep/figure.py
src/reprep/helpers.py
src/reprep/interface.py
src/reprep/mime_extensions.py
src/reprep/mpl.py
src/reprep/node.py
src/reprep/repcontracts.py
src/reprep/structures.py
src/reprep/table.py
src/reprep/types.py
src/reprep/demos/__init__.py
src/reprep/demos/colormaps.py
src/reprep/demos/demo_tests.py
src/reprep/demos/figures.py
src/reprep/demos/manager.py
src/reprep/demos/report_layout.py
src/reprep/demos/spines.py
src/reprep/demos/table.py
src/reprep/graphics/__init__.py
src/reprep/graphics/conversions.py
src/reprep/graphics/conversions_tests.py
src/reprep/graphics/filter_colormap.py
src/reprep/graphics/filter_posneg.py
src/reprep/graphics/filter_posneg_test.py
src/reprep/graphics/filter_scale.py
src/reprep/graphics/numpy_utils.py
src/reprep/graphics/scaling.py
src/reprep/graphics/success.py
src/reprep/graphics/zoom.py
src/reprep/output/__init__.py
src/reprep/output/html.py
src/reprep/output/html_test.py
src/reprep/output/hdf/__init__.py
src/reprep/output/hdf/hdf1_rawdata.py
src/reprep/output/hdf/hdf1_read.py
src/reprep/output/hdf/hdf1_write.py
src/reprep/output/hdf/hdf_read.py
src/reprep/output/hdf/test_hdf.py
src/reprep/output/ipn/__init__.py
src/reprep/output/ipn/node.py
src/reprep/plot_utils/__init__.py
src/reprep/plot_utils/axes.py
src/reprep/plot_utils/spines.py
src/reprep/plot_utils/styles.py
src/reprep/report_utils/__init__.py
src/reprep/report_utils/statistics/__init__.py
src/reprep/report_utils/statistics/library/__init__.py
src/reprep/report_utils/statistics/library/reductions.py
src/reprep/report_utils/statistics/library/reductions_display.py
src/reprep/report_utils/statistics/structures/__init__.py
src/reprep/report_utils/statistics/structures/data_view.py
src/reprep/report_utils/statistics/structures/function_with_description.py
src/reprep_z6.egg-info/PKG-INFO
src/reprep_z6.egg-info/SOURCES.txt
src/reprep_z6.egg-info/dependency_links.txt
src/reprep_z6.egg-info/entry_points.txt
src/reprep_z6.egg-info/not-zip-safe
src/reprep_z6.egg-info/requires.txt
src/reprep_z6.egg-info/top_level.txt