Metadata-Version: 1.1
Name: reprep-z6
Version: 6.0.5
Summary: Reproducible Reports
Home-page: http://AndreaCensi.github.com/reprep/
Author: Andrea Censi
Author-email: UNKNOWN
License: LGPL
Download-URL: http://github.com/AndreaCensi/reprep/tarball/6.0.5
Keywords: report reproducible research tables html latex
Platform: UNKNOWN
